wagtailquickcreate/__init__.py
wagtailquickcreate/views.py
wagtailquickcreate/wagtail_hooks.py
wagtailquickcreate/templates/wagtailquickcreate/create.html
wagtailquickcreate/templates/wagtailquickcreate/panel.html
wagtailquickcreate/tests/__init__.py
wagtailquickcreate/tests/settings.py
wagtailquickcreate/tests/tests.py
wagtailquickcreate/tests/urls.py
wagtailquickcreate/tests/standardpages/__init__.py
wagtailquickcreate/tests/standardpages/models.py
wagtailquickcreate/tests/standardpages/migrations/0001_initial.py
wagtailquickcreate/tests/standardpages/migrations/__init__.py
wagtail_quick_create-2.0.1.dist-info/LICENSE
wagtail_quick_create-2.0.1.dist-info/METADATA
wagtail_quick_create-2.0.1.dist-info/WHEEL
wagtail_quick_create-2.0.1.dist-info/top_level.txt
wagtail_quick_create-2.0.1.dist-info/RECORD
