Metadata-Version: 2.1
Name: wagtail-quick-create
Version: 2.0.1
Summary: Offer links to the admin user to create content under sections quickly.
Home-page: https://github.com/kevinhowbrook/wagtailquickcreate
Author: Kevin Howbrook - Torchbox, Kate Statton - NYPR
Author-email: kevin.howbrook@torchbox.com
License: MIT
Classifier: Environment :: Web Environment
Classifier: Intended Audience :: Developers
Classifier: Operating System :: OS Independent
Classifier: Programming Language :: Python
Classifier: Programming Language :: Python :: 3
Classifier: Programming Language :: Python :: 3.8
Classifier: Programming Language :: Python :: 3.9
Classifier: Programming Language :: Python :: 3.10
Classifier: Programming Language :: Python :: 3.11
Classifier: Framework :: Wagtail
Classifier: Framework :: Wagtail :: 4
Classifier: Framework :: Wagtail :: 5
License-File: LICENSE
Requires-Dist: wagtail (>=4.1)
